analogue/__init__.py
analogue/mcp3008.py
display/__init__.py
display/lcd.py
rasp_modules-1.0.2.dist-info/LICENSE
rasp_modules-1.0.2.dist-info/METADATA
rasp_modules-1.0.2.dist-info/WHEEL
rasp_modules-1.0.2.dist-info/top_level.txt
rasp_modules-1.0.2.dist-info/RECORD
