Metadata-Version: 2.1
Name: rasp-modules
Version: 1.0.2
Summary: It contains modules for raspberry PI.
Home-page: https://github.com/4yub1k/rasp-modules
Author: Salah Ud Din (@4yub1k)
Author-email: salahuddin@protonmail.com
License: LICENSE
Project-URL: Documentation, https://rasp-modules.readthedocs.io/en/latest/
Project-URL: Source, https://github.com/4yub1k/rasp-modules
Keywords: rasberry,rasberrypi,rasberry pi
Classifier: Development Status :: 3 - Alpha
Classifier: License :: OSI Approved :: MIT License
Classifier: Operating System :: OS Independent
Classifier: Programming Language :: Python :: 3
Requires-Python: >=3.6
License-File: LICENSE
